altair_extra_color_schemes/__init__.py
altair_extra_color_schemes/constants.py
altair_extra_color_schemes/full_template.jinja
altair_extra_color_schemes/renderer.py
altair_extra_color_schemes/template.jinja
altair_extra_color_schemes-0.2.0.dist-info/entry_points.txt
altair_extra_color_schemes-0.2.0.dist-info/LICENSE
altair_extra_color_schemes-0.2.0.dist-info/WHEEL
altair_extra_color_schemes-0.2.0.dist-info/METADATA
altair_extra_color_schemes-0.2.0.dist-info/RECORD
