Metadata-Version: 2.1
Name: altair-extra-color-schemes
Version: 0.2.0
Summary: Additional named color schemes for Altair via a custom renderer.
Home-page: https://github.com/joaopalmeiro/altair-extra-color-schemes
License: MIT
Author: João Palmeiro
Author-email: joaopalmeiro@proton.me
Requires-Python: >=3.7.1,<4.0.0
Classifier: License :: OSI Approved :: MIT License
Classifier: Programming Language :: Python :: 3
Classifier: Programming Language :: Python :: 3.8
Classifier: Programming Language :: Python :: 3.9
Classifier: Programming Language :: Python :: 3.10
Requires-Dist: altair (>=4.2,<4.3)
Project-URL: Bug Tracker, https://github.com/joaopalmeiro/altair-extra-color-schemes/issues
Project-URL: Repository, https://github.com/joaopalmeiro/altair-extra-color-schemes
Project-URL: Twitter, https://twitter.com/joaompalmeiro
